DatabaseOperations/DBOps.py
DatabaseOperations/__init__.py
DatabaseOperations-0.0.3.dist-info/LICENSE
DatabaseOperations-0.0.3.dist-info/METADATA
DatabaseOperations-0.0.3.dist-info/WHEEL
DatabaseOperations-0.0.3.dist-info/top_level.txt
DatabaseOperations-0.0.3.dist-info/RECORD
