Metadata-Version: 2.1
Name: DatabaseOperations
Version: 0.0.3
Summary: For Database Operations functions
Home-page: https://bitbucket.org/abhishekvermadeveloper/databaseoperations
Author: Abhishek Verma
Author-email: 28a.v10@gmail.com
Classifier: Programming Language :: Python :: 3
Classifier: License :: OSI Approved :: MIT License
Classifier: Operating System :: OS Independent
Requires-Python: >=3.7
License-File: LICENSE
